fix_agent-1.0.5.dist-info/licenses/LICENSE
src/__init__.py
src/__main__.py
src/main.py
src/web_app_main.py
src/web_app_stop.py
src/agents/agent.py
src/config/config.py
src/config/subagent.py
src/interface/cli.py
src/interface/commands.py
src/interface/commands_backup.py
src/interface/execution.py
src/interface/input.py
src/interface/memory_commands.py
src/midware/__init__.py
src/midware/agent_memory.py
src/midware/context_enhancement.py
src/midware/layered_memory.py
src/midware/logging.py
src/midware/memory_adapter.py
src/midware/performance_monitor.py
src/midware/security.py
src/prompt/default_agent_prompt.md
src/prompt/default_agent_prompt_en.md
src/prompt/prompt_template.py
src/prompt/prompt_template_en.py
src/tools/defect_aggregator.py
src/tools/error_detector.py
src/tools/file_ops.py
src/tools/multilang_code_analyzers.py
src/tools/network_tools.py
src/tools/network_tools_backup.py
src/tools/professional_formatter.py
src/tools/project_analyzer.py
src/tools/project_explorer.py
src/tools/test_generator.py
src/tools/tools.py
src/ui/dynamicCli.py
src/ui/ui.py
src/utils/first_time_setup.py
src/utils/token_utils.py
src/workspace/buggy_code.py
src/workspace/buggy_project.py
src/workspace/test_buggy_code.py
web_app/README.md
web_app/USAGE.md
web_app/index.html
web_app/backend/__init__.py
web_app/backend/main.py
web_app/backend/app/api/__init__.py
web_app/backend/app/api/config.py
web_app/backend/app/api/files.py
web_app/backend/app/api/memory.py
web_app/backend/app/api/projects.py
web_app/backend/app/api/sessions.py
web_app/backend/app/core/ai_adapter.py
web_app/backend/app/core/config.py
web_app/backend/app/models/database.py
web_app/backend/app/models/schemas.py
web_app/backend/app/services/session_service.py
web_app/backend/app/websocket/chat_handler.py
web_app/backend/app/websocket/connection_manager.py
web_app/frontend/package.json
fix_agent-1.0.5.dist-info/METADATA
fix_agent-1.0.5.dist-info/WHEEL
fix_agent-1.0.5.dist-info/entry_points.txt
fix_agent-1.0.5.dist-info/top_level.txt
fix_agent-1.0.5.dist-info/RECORD
