Metadata-Version: 2.4
Name: Fix_agent
Version: 1.0.5
Summary: AI Coding Assistant - 代码缺陷修复和分析工具
Author-email: 3uyuan1ee <1481059602@qq.com>
Maintainer-email: 3uyuan1ee <1481059602@qq.com>
License: MPL-2.0
Project-URL: Homepage, https://github.com/3uyuan1ee/Fix_agent
Project-URL: Documentation, https://github.com/3uyuan1ee/Fix_agent#readme
Project-URL: Repository, https://github.com/3uyuan1ee/Fix_agent
Project-URL: Bug Tracker, https://github.com/3uyuan1ee/Fix_agent/issues
Project-URL: Changelog, https://github.com/3uyuan1ee/Fix_agent/blob/main/CHANGELOG.md
Keywords: ai,coding,assistant,cli,code-analysis,bug-detection,deepagents,code-review,automated-testing,code-quality,static-analysis,python,javascript,java
Classifier: Development Status :: 3 - Alpha
Classifier: Intended Audience :: Developers
Classifier: License :: OSI Approved :: Mozilla Public License 2.0 (MPL 2.0)
Classifier: Operating System :: OS Independent
Classifier: Operating System :: Microsoft :: Windows
Classifier: Operating System :: POSIX
Classifier: Operating System :: Unix
Classifier: Operating System :: MacOS
Classifier: Programming Language :: Python :: 3
Classifier: Programming Language :: Python :: 3.11
Classifier: Programming Language :: Python :: 3.12
Classifier: Programming Language :: Python :: 3.13
Classifier: Programming Language :: Python :: 3 :: Only
Classifier: Topic :: Software Development :: Code Generators
Classifier: Topic :: Software Development :: Debuggers
Classifier: Topic :: Software Development :: Quality Assurance
Classifier: Topic :: Software Development :: Testing
Classifier: Topic :: Software Development :: Libraries :: Python Modules
Classifier: Topic :: Utilities
Classifier: Environment :: Console
Requires-Python: >=3.11
License-File: LICENSE
Requires-Dist: rich>=13.0.0
Requires-Dist: prompt-toolkit>=3.0.52
Requires-Dist: requests>=2.28.0
Requires-Dist: langchain-openai>=0.1.0
Requires-Dist: langchain==1.0.5
Requires-Dist: deepagents==0.2.6
Requires-Dist: python-dotenv>=1.0.0
Requires-Dist: langgraph>=0.1.0
Requires-Dist: tavily-python>=0.3.0
Requires-Dist: psutil>=5.9.0
Requires-Dist: pylint>=2.17.0
Requires-Dist: flake8>=6.0.0
Requires-Dist: mypy>=1.0.0
Requires-Dist: bandit>=1.7.0
Requires-Dist: black>=23.0.0
Requires-Dist: astroid>=2.15.0
Requires-Dist: isort>=5.12.0
Requires-Dist: pydocstyle>=6.0.0
Requires-Dist: lxml>=4.9.0
Requires-Dist: pyyaml>=6.0.0
Requires-Dist: toml>=0.10.0
Requires-Dist: pytest>=7.0.0
Requires-Dist: typing-extensions>=4.0.0
Provides-Extra: test
Requires-Dist: pytest>=7.0.0; extra == "test"
Requires-Dist: pytest-cov>=4.0.0; extra == "test"
Requires-Dist: pytest-mock>=3.10.0; extra == "test"
Requires-Dist: pytest-asyncio>=0.21.0; extra == "test"
Requires-Dist: pytest-xdist>=3.3.0; extra == "test"
Provides-Extra: dev
Requires-Dist: Fix_agent[test]; extra == "dev"
Requires-Dist: black>=23.0.0; extra == "dev"
Requires-Dist: flake8>=6.0.0; extra == "dev"
Requires-Dist: mypy>=1.0.0; extra == "dev"
Requires-Dist: pre-commit>=3.0.0; extra == "dev"
Provides-Extra: release
Requires-Dist: Fix_agent[dev]; extra == "release"
Requires-Dist: twine>=4.0.0; extra == "release"
Requires-Dist: wheel>=0.41.0; extra == "release"
Requires-Dist: build>=0.10.0; extra == "release"
Provides-Extra: docs
Requires-Dist: sphinx>=5.0.0; extra == "docs"
Requires-Dist: sphinx-rtd-theme>=1.2.0; extra == "docs"
Requires-Dist: myst-parser>=0.18.0; extra == "docs"
Requires-Dist: sphinx-autodoc-typehints>=1.22.0; extra == "docs"
Provides-Extra: full
Requires-Dist: Fix_agent[dev,docs,release,test]; extra == "full"
Provides-Extra: windows
Requires-Dist: Fix_agent[release]; extra == "windows"
Requires-Dist: pywin32>=226; extra == "windows"
Requires-Dist: wmi>=1.5.1; extra == "windows"
Provides-Extra: web
Requires-Dist: fastapi>=0.104.0; extra == "web"
Requires-Dist: uvicorn[standard]>=0.24.0; extra == "web"
Requires-Dist: sqlalchemy>=2.0.0; extra == "web"
Requires-Dist: alembic>=1.12.0; extra == "web"
Requires-Dist: python-jose[cryptography]>=3.3.0; extra == "web"
Requires-Dist: passlib[bcrypt]>=1.7.4; extra == "web"
Requires-Dist: python-multipart>=0.0.6; extra == "web"
Requires-Dist: aiofiles>=23.0.0; extra == "web"
Requires-Dist: psutil>=5.9.0; extra == "web"
Dynamic: license-file
